{"http://purl.org/dc/elements/1.1/identifier": ["m0wQKa"], "http://rdfs.org/ns/void#inDataset": ["http://example.net/event#alligator-mt-data"], "http://rgzm.github.io/alligator/ontology#cax": ["-0.423"], "http://rgzm.github.io/alligator/ontology#cay": ["0.549"], "http://rgzm.github.io/alligator/ontology#caz": ["0.017"], "http://rgzm.github.io/alligator/ontology#endfixed": ["true"], "http://rgzm.github.io/alligator/ontology#estimatedend": ["117.0"], "http://rgzm.github.io/alligator/ontology#estimatedstart": ["98.0"], "http://rgzm.github.io/alligator/ontology#startfixed": ["true"], "http://www.w3.org/1999/02/22-rdf-syntax-ns#type": ["http://rgzm.github.io/alligator/ontology#event", "http://www.w3.org/2006/time#Interval"], "http://www.w3.org/2000/01/rdf-schema#label": ["Trajan"], "http://www.w3.org/2006/time#intervalAfter": ["http://example.net/event#egQg43", "http://example.net/event#Ydvg7G", "http://example.net/event#BwyQ6x", "http://example.net/event#VAvO57"], "http://www.w3.org/2006/time#intervalDuring": ["http://example.net/event#VJALzd"], "http://www.w3.org/2006/time#intervalMetBy": ["http://example.net/event#Mo7Blr"], "http://www.w3.org/2006/time#intervalOverlappedBy": ["http://example.net/event#wBJxqV"]}